template_string_logger-1.0.dist-info/licenses/LICENSE
tstring_logger/__init__.py
tstring_logger/main.py
tstring_logger/t.py
template_string_logger-1.0.dist-info/METADATA
template_string_logger-1.0.dist-info/WHEEL
template_string_logger-1.0.dist-info/entry_points.txt
template_string_logger-1.0.dist-info/top_level.txt
template_string_logger-1.0.dist-info/RECORD
