Metadata-Version: 2.4
Name: template-string-logger
Version: 1.0
Summary: Python logger that supports t-strings
Author: Gerard
Author-email: gweatherby@uchc.edu
License: MIT
Project-URL: Homepage, https://github.com/NMRhub/tstring-logger
Project-URL: Repository, https://github.com/NMRhub/tstring-logger
Project-URL: Issues, https://github.com/NMRhub/tstring-logger/issues
Project-URL: Changelog, https://github.com/NMRhub/tstring-logger/releases
Requires-Python: >=3.14
License-File: LICENSE
Requires-Dist: tstring-util>=2.1
Dynamic: license-file
